fertilizer/__init__.py
fertilizer/api.py
fertilizer/args.py
fertilizer/config.py
fertilizer/config_validator.py
fertilizer/errors.py
fertilizer/filesystem.py
fertilizer/injection.py
fertilizer/main.py
fertilizer/parser.py
fertilizer/progress.py
fertilizer/scanner.py
fertilizer/torrent.py
fertilizer/trackers.py
fertilizer/utils.py
fertilizer/webserver.py
fertilizer/clients/deluge.py
fertilizer/clients/qbittorrent.py
fertilizer/clients/torrent_client.py
fertilizer/clients/transmission.py
fertilizer-0.3.0.dist-info/LICENSE
fertilizer-0.3.0.dist-info/METADATA
fertilizer-0.3.0.dist-info/WHEEL
fertilizer-0.3.0.dist-info/entry_points.txt
fertilizer-0.3.0.dist-info/top_level.txt
fertilizer-0.3.0.dist-info/RECORD
