Metadata-Version: 2.1
Name: fertilizer
Version: 0.3.0
Summary: fertilizer helps your seeds grow
Requires-Python: >=3.11
License-File: LICENSE
Requires-Dist: bencoder
Requires-Dist: colorama
Requires-Dist: requests
Requires-Dist: flask
Provides-Extra: dev
Requires-Dist: pytest; extra == "dev"
Requires-Dist: ruff; extra == "dev"
Requires-Dist: requests-mock; extra == "dev"
